CanvasDrawOnTheWeb/README.md
CanvasDrawOnTheWeb/__init__.py
CanvasDrawOnTheWeb/__main__.py
CanvasDrawOnTheWeb/file.epub
CanvasDrawOnTheWeb/index.html
CanvasDrawOnTheWeb/css/__init__.py
CanvasDrawOnTheWeb/css/annotations.css
CanvasDrawOnTheWeb/css/main.css
CanvasDrawOnTheWeb/css/normalize.css
CanvasDrawOnTheWeb/css/popup.css
CanvasDrawOnTheWeb/font/__init__.py
CanvasDrawOnTheWeb/font/fontello.eot
CanvasDrawOnTheWeb/font/fontello.svg
CanvasDrawOnTheWeb/font/fontello.ttf
CanvasDrawOnTheWeb/font/fontello.woff
CanvasDrawOnTheWeb/img/__init__.py
CanvasDrawOnTheWeb/img/annotator-glyph-sprite.png
CanvasDrawOnTheWeb/img/annotator-icon-sprite.png
CanvasDrawOnTheWeb/img/apple-touch-icon.png
CanvasDrawOnTheWeb/img/cancelfullscreen.png
CanvasDrawOnTheWeb/img/close.png
CanvasDrawOnTheWeb/img/fullscreen.png
CanvasDrawOnTheWeb/img/loader.gif
CanvasDrawOnTheWeb/img/menu-icon.png
CanvasDrawOnTheWeb/img/save.png
CanvasDrawOnTheWeb/img/saved.png
CanvasDrawOnTheWeb/img/settings-s.png
CanvasDrawOnTheWeb/img/settings.png
CanvasDrawOnTheWeb/img/star.png
CanvasDrawOnTheWeb/js/__init__.py
CanvasDrawOnTheWeb/js/epub.js
CanvasDrawOnTheWeb/js/epub.min.js
CanvasDrawOnTheWeb/js/epub.min.map
CanvasDrawOnTheWeb/js/hooks.min.js
CanvasDrawOnTheWeb/js/hooks.min.map
CanvasDrawOnTheWeb/js/reader.js
CanvasDrawOnTheWeb/js/reader.js.map
CanvasDrawOnTheWeb/js/reader.min.js
CanvasDrawOnTheWeb/js/reader.min.map
CanvasDrawOnTheWeb/js/hooks/__init__.py
CanvasDrawOnTheWeb/js/hooks/extensions/__init__.py
CanvasDrawOnTheWeb/js/hooks/extensions/highlight.js
CanvasDrawOnTheWeb/js/libs/__init__.py
CanvasDrawOnTheWeb/js/libs/jquery.min.js
CanvasDrawOnTheWeb/js/libs/localforage.min.js
CanvasDrawOnTheWeb/js/libs/screenfull.js
CanvasDrawOnTheWeb/js/libs/screenfull.min.js
CanvasDrawOnTheWeb/js/libs/zip.min.js
CanvasDrawOnTheWeb/js/plugins/__init__.py
CanvasDrawOnTheWeb/js/plugins/hypothesis.js
CanvasDrawOnTheWeb/js/plugins/search.js
canvas_draw_on_the_web-2024.3.1.0.dist-info/METADATA
canvas_draw_on_the_web-2024.3.1.0.dist-info/WHEEL
canvas_draw_on_the_web-2024.3.1.0.dist-info/entry_points.txt
canvas_draw_on_the_web-2024.3.1.0.dist-info/top_level.txt
canvas_draw_on_the_web-2024.3.1.0.dist-info/RECORD
